{
  "name": "puppet-confluent_kafka",
  "version": "0.3.0",
  "author": "Chartbeat",
  "summary": "Installs Confluent's Kafka Package",
  "license": "MIT",
  "source": "http://github.com/chartbeat-labs/puppet-confluent-kafka",
  "project_page": "https://github.com/chartbeat-labs/puppet-confluent-kafka",
  "issues_url": "https://github.com/chartbeat-labs/puppet-confluent-kafka/issues",
  "dependencies": [
    {
      "name": "puppetlabs-stdlib",
      "version_requirement": ">= 4.5.1"
    },
    {
      "name": "puppetlabs-apt",
      "version_requirement": "1.8.0"
    }
  ],
  "operatingsystem_support": [
    {
      "operatingsystem": "Debian",
      "operatingsystemrelease": [
        "6",
        "7"
      ]
    }
  ]
}
